fleet/__init__.py
fleet/_base_client.py
fleet/_client.py
fleet/_compat.py
fleet/_constants.py
fleet/_exceptions.py
fleet/_files.py
fleet/_models.py
fleet/_qs.py
fleet/_resource.py
fleet/_response.py
fleet/_streaming.py
fleet/_types.py
fleet/_version.py
fleet/py.typed
fleet/_utils/__init__.py
fleet/_utils/_compat.py
fleet/_utils/_datetime_parse.py
fleet/_utils/_logs.py
fleet/_utils/_proxy.py
fleet/_utils/_reflection.py
fleet/_utils/_resources_proxy.py
fleet/_utils/_streams.py
fleet/_utils/_sync.py
fleet/_utils/_transform.py
fleet/_utils/_typing.py
fleet/_utils/_utils.py
fleet/lib/.keep
fleet/resources/__init__.py
fleet/resources/health.py
fleet/resources/sessions/__init__.py
fleet/resources/sessions/page.py
fleet/resources/sessions/responses.py
fleet/resources/sessions/sessions.py
fleet/resources/sessions/start.py
fleet/resources/sessions/scrape/__init__.py
fleet/resources/sessions/scrape/async_.py
fleet/resources/sessions/scrape/browser_strategy.py
fleet/resources/sessions/scrape/scrape.py
fleet/resources/vnc/__init__.py
fleet/resources/vnc/discovery.py
fleet/resources/vnc/sessions.py
fleet/resources/vnc/vnc.py
fleet/resources/workflows/__init__.py
fleet/resources/workflows/workflows.py
fleet/resources/workflows/request/__init__.py
fleet/resources/workflows/request/mass.py
fleet/resources/workflows/request/request.py
fleet/types/__init__.py
fleet/types/browser_configuration_param.py
fleet/types/session_create_params.py
fleet/types/session_create_response.py
fleet/types/session_delete_response.py
fleet/types/session_list_response.py
fleet/types/session_retrieve_response.py
fleet/types/session_visit_page_params.py
fleet/types/session_visit_page_response.py
fleet/types/session_warm_up_response.py
fleet/types/workflow_describe_response.py
fleet/types/workflow_results_response.py
fleet/types/sessions/__init__.py
fleet/types/sessions/browser_selection_strategy.py
fleet/types/sessions/page_get_full_response.py
fleet/types/sessions/page_get_response.py
fleet_client-0.12.0.dist-info/METADATA
fleet_client-0.12.0.dist-info/WHEEL
fleet_client-0.12.0.dist-info/licenses/LICENSE
fleet_client-0.12.0.dist-info/RECORD
